LCRUD/__init__.py
LCRUD/lcrud.py
LCRUD-1.0.1.dist-info/METADATA
LCRUD-1.0.1.dist-info/WHEEL
LCRUD-1.0.1.dist-info/top_level.txt
LCRUD-1.0.1.dist-info/RECORD
