Metadata-Version: 2.1
Name: LCRUD
Version: 1.0.1
Summary: Uma biblioteca para operações LCRUD em arquivos Excel.
Author: Leonardo
Author-email: leonardonery616@gmail.com
Classifier: Programming Language :: Python :: 3
Classifier: License :: OSI Approved :: MIT License
Classifier: Operating System :: OS Independent
Requires-Python: >=3.6
Requires-Dist: openpyxl
